feeed/__init__.py
feeed/activities.py
feeed/end_activities.py
feeed/epa_based.py
feeed/eventropies.py
feeed/feature.py
feeed/feature_extractor.py
feeed/simple_stats.py
feeed/start_activities.py
feeed/time.py
feeed/trace_length.py
feeed/trace_variant.py
feeed/utils/__init__.py
feeed/utils/feature_names.py
feeed/utils/sort_alphanumeric.py
feeed-1.3.2.dist-info/LICENSE
feeed-1.3.2.dist-info/METADATA
feeed-1.3.2.dist-info/WHEEL
feeed-1.3.2.dist-info/top_level.txt
feeed-1.3.2.dist-info/RECORD
