Metadata-Version: 2.1
Name: feeed
Version: 1.3.2
Summary: Feature Extraction from Event Data
Home-page: https://github.com/lmu-dbs/feeed.git
Author: Andrea Maldonado, Gabriel Tavares
Author-email: andreamalher.works@gmail.com, gabrielmrqstvrs@gmail.com
License: MIT
Platform: UNKNOWN
Classifier: Development Status :: 3 - Alpha
Classifier: Intended Audience :: Science/Research
Classifier: Topic :: Software Development
Classifier: License :: OSI Approved :: MIT License
Classifier: Programming Language :: Python :: 3.9
License-File: LICENSE
Requires-Dist: tqdm==4.65.0
Requires-Dist: pm4py==2.7.2
Requires-Dist: scipy>=1.10.1
Requires-Dist: Levenshtein==0.23.0
